README.rst
setup.py
toastedmarshmallow_enum/__init__.py
toastedmarshmallow_enum.egg-info/PKG-INFO
toastedmarshmallow_enum.egg-info/SOURCES.txt
toastedmarshmallow_enum.egg-info/dependency_links.txt
toastedmarshmallow_enum.egg-info/not-zip-safe
toastedmarshmallow_enum.egg-info/requires.txt
toastedmarshmallow_enum.egg-info/top_level.txt