Metadata-Version: 1.1
Name: toastedmarshmallow-enum
Version: 1.0.0
Summary: ['The Toasted Marshmallow Enum package makes it possible to dump and load Enum values based on the ultra fast serialization that Toasted Marshmallow provides.']
Home-page: https://gitlab.com/py-ddd/toastedmarshmallow-enum
Author: Victor Klapholz
Author-email: victor.klapholz@gmail.com
License: apache2
Keywords: serialization,rest,json,api,marshal,marshalling,deserialization,validation,schema,toastedmarshmallow,enum
Platform: UNKNOWN
Classifier: Development Status :: 5 - Production/Stable
Classifier: Intended Audience :: Developers
Classifier: License :: OSI Approved :: Apache Software License
Classifier: Programming Language :: Python :: 3.6
Classifier: Programming Language :: Python :: Implementation :: CPython
Classifier: Programming Language :: Python :: Implementation :: PyPy
